lnbfx/__init__.py
lnbfx/_core.py
lnbfx/_lookup.py
lnbfx/datasets.py
lnbfx/dev/__init__.py
lnbfx/dev/_core.py
lnbfx/dev/_sc.py
lnbfx/schema/__init__.py
lnbfx/schema/_core.py
lnbfx/schema/alembic.ini
lnbfx/schema/dev/__init__.py
lnbfx/schema/dev/_id.py
lnbfx/schema/dev/_versions.py
lnbfx/schema/dev/id.py
lnbfx/schema/migrations/env.py
lnbfx/schema/migrations/script.py.mako
lnbfx/schema/migrations/versions/2022-11-03-cfda12fc80a8-v0_5_0.py
lnbfx/schema/migrations/versions/2022-11-11-b93449654dce-v0_7_0.py
lnbfx-0.7.1.dist-info/LICENSE
lnbfx-0.7.1.dist-info/WHEEL
lnbfx-0.7.1.dist-info/METADATA
lnbfx-0.7.1.dist-info/RECORD
