Metadata-Version: 2.1
Name: lnbfx
Version: 0.7.1
Summary: Manage bioinformatics pipelines.
Author-email: Lamin Labs <laminlabs@gmail.com>
Requires-Dist: nbproject
Requires-Dist: sqlmodel
Requires-Dist: lnschema_core>=0.9.0
Requires-Dist: pre-commit ; extra == "dev"
Requires-Dist: nox ; extra == "dev"
Requires-Dist: pytest>=6.0 ; extra == "test"
Requires-Dist: pytest-cov ; extra == "test"
Project-URL: Home, https://github.com/laminlabs/lnbfx
Provides-Extra: dev
Provides-Extra: test
